pyspark_helpers/__init__.py
pyspark_helpers/schema.py
pyspark_helpers/utils.py
pyspark_helpers-0.2.1.dist-info/METADATA
pyspark_helpers-0.2.1.dist-info/WHEEL
pyspark_helpers-0.2.1.dist-info/entry_points.txt
pyspark_helpers-0.2.1.dist-info/RECORD
