Metadata-Version: 2.1
Name: pyspark-helpers
Version: 0.2.1
Summary: A collection of tools to help when developing PySpark applications
Author: Jens Peder Meldgaard
Author-email: jenspederm@gmail.com
Requires-Python: >=3.8,<4.0
Classifier: Programming Language :: Python :: 3
Classifier: Programming Language :: Python :: 3.8
Classifier: Programming Language :: Python :: 3.9
Classifier: Programming Language :: Python :: 3.10
Classifier: Programming Language :: Python :: 3.11
Requires-Dist: black (>=23.7.0,<24.0.0)
Requires-Dist: delta-spark (>=2.2.0,<3.0.0)
Requires-Dist: pyspark (>=3.3.2,<4.0.0)
